[
  {
    "name": "ai-waste-sorter-",
    "html_url": "https://github.com/ananthakrishnan754/ai-waste-sorter-",
    "stargazers_count": 0,
    "language": "Python"
  },
  {
    "name": "Bloe-to-glow",
    "html_url": "https://github.com/ananthakrishnan754/Bloe-to-glow",
    "stargazers_count": 0,
    "language": "JavaScript"
  },
  {
    "name": "Deep-learning-based-real-time-face-recognization-system-for-alzheimer-s-patients",
    "html_url": "https://github.com/ananthakrishnan754/Deep-learning-based-real-time-face-recognization-system-for-alzheimer-s-patients",
    "stargazers_count": 0,
    "language": "Python"
  },
  {
    "name": "desk-display",
    "html_url": "https://github.com/ananthakrishnan754/desk-display",
    "stargazers_count": 0,
    "language": "HTML"
  },
  {
    "name": "esp32-max7299-clock-cpu-ram-monitor",
    "html_url": "https://github.com/ananthakrishnan754/esp32-max7299-clock-cpu-ram-monitor",
    "stargazers_count": 0,
    "language": null
  },
  {
    "name": "fuelsense",
    "html_url": "https://github.com/ananthakrishnan754/fuelsense",
    "stargazers_count": 0,
    "language": null
  },
  {
    "name": "ICAISN",
    "html_url": "https://github.com/ananthakrishnan754/ICAISN",
    "stargazers_count": 0,
    "language": "HTML"
  },
  {
    "name": "ICFISN-2026",
    "html_url": "https://github.com/ananthakrishnan754/ICFISN-2026",
    "stargazers_count": 0,
    "language": "HTML"
  },
  {
    "name": "ICRCS",
    "html_url": "https://github.com/ananthakrishnan754/ICRCS",
    "stargazers_count": 0,
    "language": "HTML"
  },
  {
    "name": "ICST2025",
    "html_url": "https://github.com/ananthakrishnan754/ICST2025",
    "stargazers_count": 0,
    "language": "HTML"
  },
  {
    "name": "krixxAi",
    "html_url": "https://github.com/ananthakrishnan754/krixxAi",
    "stargazers_count": 0,
    "language": "JavaScript"
  },
  {
    "name": "mylove",
    "html_url": "https://github.com/ananthakrishnan754/mylove",
    "stargazers_count": 0,
    "language": "HTML"
  },
  {
    "name": "nukelab--",
    "html_url": "https://github.com/ananthakrishnan754/nukelab--",
    "stargazers_count": 0,
    "language": null
  },
  {
    "name": "nukelab-test",
    "html_url": "https://github.com/ananthakrishnan754/nukelab-test",
    "stargazers_count": 0,
    "language": "JavaScript"
  },
  {
    "name": "port2",
    "html_url": "https://github.com/ananthakrishnan754/port2",
    "stargazers_count": 0,
    "language": "HTML"
  },
  {
    "name": "portfolio1",
    "html_url": "https://github.com/ananthakrishnan754/portfolio1",
    "stargazers_count": 0,
    "language": "HTML"
  },
  {
    "name": "Predator-Helios-16-Linux-Control-Center",
    "html_url": "https://github.com/ananthakrishnan754/Predator-Helios-16-Linux-Control-Center",
    "stargazers_count": 0,
    "language": null
  },
  {
    "name": "resume-",
    "html_url": "https://github.com/ananthakrishnan754/resume-",
    "stargazers_count": 0,
    "language": "HTML"
  },
  {
    "name": "review-flow",
    "html_url": "https://github.com/ananthakrishnan754/review-flow",
    "stargazers_count": 0,
    "language": "TypeScript"
  },
  {
    "name": "rklab",
    "html_url": "https://github.com/ananthakrishnan754/rklab",
    "stargazers_count": 0,
    "language": "CSS"
  },
  {
    "name": "starter-kit",
    "html_url": "https://github.com/ananthakrishnan754/starter-kit",
    "stargazers_count": 0,
    "language": "HTML"
  },
  {
    "name": "tic-tac-toe",
    "html_url": "https://github.com/ananthakrishnan754/tic-tac-toe",
    "stargazers_count": 0,
    "language": "HTML"
  },
  {
    "name": "time-traveller",
    "html_url": "https://github.com/ananthakrishnan754/time-traveller",
    "stargazers_count": 0,
    "language": "Python"
  },
  {
    "name": "TODO",
    "html_url": "https://github.com/ananthakrishnan754/TODO",
    "stargazers_count": 0,
    "language": "HTML"
  },
  {
    "name": "walkie",
    "html_url": "https://github.com/ananthakrishnan754/walkie",
    "stargazers_count": 0,
    "language": null
  },
  {
    "name": "WhatsApp-Summarizer",
    "html_url": "https://github.com/ananthakrishnan754/WhatsApp-Summarizer",
    "stargazers_count": 0,
    "language": "HTML"
  },
  {
    "name": "XBOX-FAEK",
    "html_url": "https://github.com/ananthakrishnan754/XBOX-FAEK",
    "stargazers_count": 0,
    "language": "CSS"
  }
]
